TG_AutoPoster/TG_AutoPoster.py
TG_AutoPoster/__init__.py
TG_AutoPoster/__main__.py
TG_AutoPoster/plugins/__init__.py
TG_AutoPoster/plugins/callback.py
TG_AutoPoster/plugins/commands.py
TG_AutoPoster/plugins/handlers.py
TG_AutoPoster/plugins/inline.py
TG_AutoPoster/utils/__init__.py
TG_AutoPoster/utils/tools.py
TG_AutoPoster/utils/tg/__init__.py
TG_AutoPoster/utils/tg/messages.py
TG_AutoPoster/utils/tg/tools.py
TG_AutoPoster/utils/vk/__init__.py
TG_AutoPoster/utils/vk/group.py
TG_AutoPoster/utils/vk/handlers.py
TG_AutoPoster/utils/vk/parser.py
TG_AutoPoster/utils/vk/sender.py
TG_AutoPoster/utils/vk/tools.py
jconfig/__init__.py
jconfig/base.py
jconfig/jconfig.py
jconfig/memory.py
tg_autoposter-3.6.1.dist-info/licenses/LICENCE.md
vk_api/__init__.py
vk_api/audio.py
vk_api/audio_url_decoder.py
vk_api/bot_longpoll.py
vk_api/credentials.py
vk_api/enums.py
vk_api/exceptions.py
vk_api/execute.py
vk_api/keyboard.py
vk_api/longpoll.py
vk_api/requests_pool.py
vk_api/streaming.py
vk_api/tools.py
vk_api/upload.py
vk_api/utils.py
vk_api/vk_api.py
tg_autoposter-3.6.1.dist-info/METADATA
tg_autoposter-3.6.1.dist-info/WHEEL
tg_autoposter-3.6.1.dist-info/top_level.txt
tg_autoposter-3.6.1.dist-info/RECORD
