Metadata-Version: 2.4
Name: TG_AutoPoster
Version: 3.6.1
Summary: Telegram Bot for reposting from VK
Home-page: https://github.com/qwertyadrian/TG_AutoPoster
Download-URL: https://github.com/qwertyadrian/TG_AutoPoster/releases/latest
Author: qwertyadrian
Author-email: me@qwertyadrian.ru
License: MIT License
Platform: OS Independent
Classifier: License :: OSI Approved :: MIT License
Classifier: Operating System :: OS Independent
Classifier: Programming Language :: Python
Classifier: Programming Language :: Python :: 3 :: Only
Classifier: Programming Language :: Python :: 3.8
Classifier: Programming Language :: Python :: 3.9
Classifier: Programming Language :: Python :: 3.10
Classifier: Programming Language :: Python :: 3.11
Classifier: Programming Language :: Python :: 3.12
Classifier: Programming Language :: Python :: 3.13
Classifier: Programming Language :: Python :: 3.14
Classifier: Programming Language :: Python :: Implementation :: CPython
Classifier: Topic :: Internet
Classifier: Topic :: Communications
Classifier: Topic :: Communications :: Chat
Requires-Python: ~=3.8
License-File: LICENCE.md
Requires-Dist: kurigram==2.2.13
Requires-Dist: tgcrypto
Requires-Dist: loguru==0.7.3
Requires-Dist: wget==3.2
Requires-Dist: mutagen==1.47.0
Requires-Dist: beautifulsoup4==4.14.2
Requires-Dist: apscheduler==3.11.0
Requires-Dist: pyyaml==6.0.3
Requires-Dist: m3u8==6.0.0
Requires-Dist: pycryptodome==3.23.0
Requires-Dist: moviepy==2.2.1
Requires-Dist: requests<3.0.0,>=2.20.0
Dynamic: author
Dynamic: author-email
Dynamic: classifier
Dynamic: description
Dynamic: description-content-type
Dynamic: download-url
Dynamic: home-page
Dynamic: license
Dynamic: license-file
Dynamic: platform
Dynamic: requires-dist
Dynamic: requires-python
Dynamic: summary
